[{"line":2,"elements":[{"start_timestamp":"2023-04-19T07:04:27.204Z","line":5,"name":"Kullanici ders secebilmelidir","description":"","id":"vice-dean-ders-secebilmeli;kullanici-ders-secebilmelidir","type":"scenario","keyword":"Scenario","steps":[{"result":{"error_message":"org.openqa.selenium.NoSuchElementException: no such element: Unable to locate element: {\"method\":\"xpath\",\"selector\":\"//button[@id='controlled-tab-example-tab-lessonProgram']\"}\n  (Session info: chrome=112.0.5615.121)\nFor documentation on this error, please visit: https://selenium.dev/exceptions/#no_such_element\nBuild info: version: '4.8.3', revision: 'e5e76298c3'\nSystem info: os.name: 'Windows 11', os.arch: 'amd64', os.version: '10.0', java.version: '11.0.17'\nDriver info: org.openqa.selenium.chrome.ChromeDriver\nCommand: [fc41cfe61c52033bd41e33d9fadc9d79, findElement {using=xpath, value=//button[@id='controlled-tab-example-tab-lessonProgram']}]\nCapabilities {acceptInsecureCerts: false, browserName: chrome, browserVersion: 112.0.5615.121, chrome: {chromedriverVersion: 112.0.5615.49 (bd2a7bcb881c..., userDataDir: C:\\Users\\cvlci\\AppData\\Loca...}, goog:chromeOptions: {debuggerAddress: localhost:56764}, networkConnectionEnabled: false, pageLoadStrategy: normal, platformName: WINDOWS, proxy: Proxy(), se:cdp: ws://localhost:56764/devtoo..., se:cdpVersion: 112.0.5615.121, setWindowRect: true, strictFileInteractability: false, timeouts: {implicit: 0, pageLoad: 300000, script: 30000}, unhandledPromptBehavior: dismiss and notify, webauthn:extension:credBlob: true, webauthn:extension:largeBlob: true, webauthn:extension:minPinLength: true, webauthn:extension:prf: true, webauthn:virtualAuthenticators: true}\nSession ID: fc41cfe61c52033bd41e33d9fadc9d79\r\n\tat java.base/jdk.internal.reflect.NativeConstructorAccessorImpl.newInstance0(Native Method)\r\n\tat java.base/jdk.internal.reflect.NativeConstructorAccessorImpl.newInstance(NativeConstructorAccessorImpl.java:62)\r\n\tat java.base/jdk.internal.reflect.DelegatingConstructorAccessorImpl.newInstance(DelegatingConstructorAccessorImpl.java:45)\r\n\tat java.base/java.lang.reflect.Constructor.newInstance(Constructor.java:490)\r\n\tat org.openqa.selenium.remote.codec.w3c.W3CHttpResponseCodec.createException(W3CHttpResponseCodec.java:200)\r\n\tat org.openqa.selenium.remote.codec.w3c.W3CHttpResponseCodec.decode(W3CHttpResponseCodec.java:133)\r\n\tat org.openqa.selenium.remote.codec.w3c.W3CHttpResponseCodec.decode(W3CHttpResponseCodec.java:53)\r\n\tat org.openqa.selenium.remote.HttpCommandExecutor.execute(HttpCommandExecutor.java:193)\r\n\tat org.openqa.selenium.remote.service.DriverCommandExecutor.invokeExecute(DriverCommandExecutor.java:183)\r\n\tat org.openqa.selenium.remote.service.DriverCommandExecutor.execute(DriverCommandExecutor.java:158)\r\n\tat org.openqa.selenium.remote.RemoteWebDriver.execute(RemoteWebDriver.java:543)\r\n\tat org.openqa.selenium.remote.ElementLocation$ElementFinder$2.findElement(ElementLocation.java:162)\r\n\tat org.openqa.selenium.remote.ElementLocation.findElement(ElementLocation.java:60)\r\n\tat org.openqa.selenium.remote.RemoteWebDriver.findElement(RemoteWebDriver.java:352)\r\n\tat org.openqa.selenium.remote.RemoteWebDriver.findElement(RemoteWebDriver.java:344)\r\n\tat org.openqa.selenium.support.pagefactory.DefaultElementLocator.findElement(DefaultElementLocator.java:70)\r\n\tat org.openqa.selenium.support.pagefactory.internal.LocatingElementHandler.invoke(LocatingElementHandler.java:39)\r\n\tat com.sun.proxy.$Proxy25.click(Unknown Source)\r\n\tat stepdefinitions.uidefinitions.US10StepDefinition.kullanici_lessons_programi_tiklar(US10StepDefinition.java:20)\r\n\tat ✽.Kullanici  lessons Programi tiklar(file:///C:/Users/cvlci/IdeaProjects/CucumberProjectTeam20/./src/test/resources/features/uifeature/US10.feature:7)\r\n","duration":19778555200,"status":"failed"},"line":7,"name":"Kullanici  lessons Programi tiklar","match":{"location":"stepdefinitions.uidefinitions.US10StepDefinition.kullanici_lessons_programi_tiklar()"},"keyword":"And "},{"result":{"status":"skipped"},"line":8,"name":"User select lessoni tıklar","match":{"location":"stepdefinitions.uidefinitions.US10StepDefinition.user_select_lessoni_tıklar()"},"keyword":"And "},{"result":{"status":"skipped"},"line":9,"name":"acılan ders listesinden ders secer","match":{"location":"stepdefinitions.uidefinitions.US10StepDefinition.acılan_ders_listesinden_ders_acılan_ders_listesinden_ders_secersecer()"},"keyword":"And "},{"result":{"status":"skipped"},"line":10,"name":"Education Term i secer","match":{"location":"stepdefinitions.uidefinitions.US10StepDefinition.education_term_secer()"},"keyword":"And "},{"result":{"status":"skipped"},"line":11,"name":"acilan menuden SPRİNG_SEMESTERi secer","match":{"location":"stepdefinitions.uidefinitions.US10StepDefinition.acilan_menuden_spring_semeste_ri_secer()"},"keyword":"And "},{"result":{"status":"skipped"},"line":12,"name":"CHOOSE DAYii tiklar","match":{"location":"stepdefinitions.uidefinitions.US10StepDefinition.choose_da_yii_tıklar()"},"keyword":"And "},{"result":{"status":"skipped"},"line":13,"name":"acilan menuden Mondayi tiklar","match":{"location":"stepdefinitions.uidefinitions.US10StepDefinition.acilan_menuden_mondayi_tıklar()"},"keyword":"And "},{"result":{"duration":7007500,"status":"skipped"},"line":14,"name":"Start Time i tiklar","match":{"location":"stepdefinitions.uidefinitions.US10StepDefinition.start_time_i_tıklar()"},"keyword":"And "},{"result":{"status":"skipped"},"line":15,"name":"gecerli bir saat degeri girer","match":{"location":"stepdefinitions.uidefinitions.US10StepDefinition.gecerli_bir_saat_degeri_girer()"},"keyword":"And "},{"result":{"status":"skipped"},"line":16,"name":"Stop Time i tiklar","match":{"location":"stepdefinitions.uidefinitions.US10StepDefinition.stop_time_i_tiklar()"},"keyword":"And "},{"result":{"status":"skipped"},"line":17,"name":"gecerli bir saat degeri girer","match":{"location":"stepdefinitions.uidefinitions.US10StepDefinition.gecerli_bir_saat_degeri_girer()"},"keyword":"And "},{"result":{"status":"skipped"},"line":18,"name":"close driver","match":{"location":"stepdefinitions.uidefinitions.LoginStepDefinitions.close_driver()"},"keyword":"Then "}],"tags":[{"name":"@US10"}]}],"name":"Vice dean ders secebilmeli","description":"   Given Kullanici viceDean olarak login olur.","id":"vice-dean-ders-secebilmeli","keyword":"Feature","uri":"file:src/test/resources/features/uifeature/US10.feature","tags":[{"name":"@US10","type":"Tag","location":{"line":1,"column":1}}]},{"line":2,"elements":[{"start_timestamp":"2023-04-19T07:04:47.362Z","line":6,"name":"Kullanici ders secebilmelidir#","description":"","id":"teacher--öğrencilere-not-verebilmelidir.;kullanici-ders-secebilmelidir#","type":"scenario","keyword":"Scenario","steps":[{"result":{"duration":6426780300,"status":"passed"},"line":7,"name":"Kullanici Teacher olarak login olur.","match":{"location":"stepdefinitions.uidefinitions.LoginStepDefinitions.kullanici_teacher_olarak_login_olur()"},"keyword":"Given "},{"result":{"duration":1957225300,"status":"passed"},"line":8,"name":"choose lesson tiklar","match":{"location":"stepdefinitions.uidefinitions.US17StepDefinition.choose_lesson_tiklar()"},"keyword":"Given "},{"result":{"duration":1274731800,"status":"passed"},"line":10,"name":"acilan Student Info Management sayfasindan Choose Education Term ı tiklar","match":{"location":"stepdefinitions.uidefinitions.US17StepDefinition.acılan_student_ınfo_management_sayfasından_choose_education_term_ı_tıklar()"},"keyword":"And "},{"result":{"duration":1093160500,"status":"passed"},"line":11,"name":"acilan menuden bir ogretim donemi secer","match":{"location":"stepdefinitions.uidefinitions.US17StepDefinition.acılan_menuden_bir_ogretim_donemi_secer()"},"keyword":"And "},{"result":{"duration":1137567400,"status":"passed"},"line":12,"name":"acilan Student Info Management sayfasından Absentee ye tiklar","match":{"location":"stepdefinitions.uidefinitions.US17StepDefinition.acılan_student_ınfo_management_sayfasından_absentee_ye_tıklar()"},"keyword":"And "},{"result":{"duration":1077105000,"status":"passed"},"line":13,"name":"ogrencinin kac gun  devamsizlik yaptigini girer","match":{"location":"stepdefinitions.uidefinitions.US17StepDefinition.ogrencinin_kac_gun_devamsızlık_yaptıgını_girer()"},"keyword":"And "},{"result":{"duration":1147092400,"status":"passed"},"line":14,"name":"acilan Student Info Management sayfasından Midterm Exam a tiklar","match":{"location":"stepdefinitions.uidefinitions.US17StepDefinition.acılan_student_ınfo_management_sayfasından_midterm_exam_a_tıklar()"},"keyword":"Given "},{"result":{"duration":1087614900,"status":"passed"},"line":15,"name":"Midterm exam kısmına bir ara sınav Notu girer","match":{"location":"stepdefinitions.uidefinitions.US17StepDefinition.midterm_exam_kısmına_bir_ara_sınav_notu_girer()"},"keyword":"Given "},{"result":{"duration":1129258000,"status":"passed"},"line":16,"name":"acilan Student Info Management sayfasindan Final Exam a tiklar","match":{"location":"stepdefinitions.uidefinitions.US17StepDefinition.acılan_student_ınfo_management_sayfasından_final_exam_a_tıklar()"},"keyword":"Given "},{"result":{"duration":1083090000,"status":"passed"},"line":17,"name":"Final exam kismina bir final Notu girer","match":{"location":"stepdefinitions.uidefinitions.US17StepDefinition.final_exam_kısmına_bir_final_notu_girer()"},"keyword":"Given "},{"result":{"duration":1100873400,"status":"passed"},"line":18,"name":"acilan Student Info Management sayfasından Info Note a tiklar","match":{"location":"stepdefinitions.uidefinitions.US17StepDefinition.acılan_student_ınfo_management_sayfasından_ınfo_note_a_tıklar()"},"keyword":"Given "},{"result":{"duration":1125749200,"status":"passed"},"line":19,"name":"Info Note kısmına bir bilgi notu girer","match":{"location":"stepdefinitions.uidefinitions.US17StepDefinition.ınfo_note_kısmına_bir_bilgi_notu_girer()"},"keyword":"Given "}],"tags":[{"name":"@US10"}]}],"name":"Teacher, öğrencilere not verebilmelidir.","description":"","id":"teacher--öğrencilere-not-verebilmelidir.","keyword":"Feature","uri":"file:src/test/resources/features/uifeature/US17.feature","tags":[{"name":"@US10","type":"Tag","location":{"line":1,"column":1}}]}]